rikka/__init__.py
rikka/config.py
rikka/exceptions.py
rikka/local.py
rikka/logger.py
rikka/protocol.py
rikka/server.py
rikka/utils.py
rikka-1.0.dist-info/METADATA
rikka-1.0.dist-info/RECORD
rikka-1.0.dist-info/WHEEL
rikka-1.0.dist-info/entry_points.txt
rikka-1.0.dist-info/top_level.txt
