Metadata-Version: 2.1
Name: rikka
Version: 1.0
Summary: Expose localhost to public Internet
Home-page: https://github.com/Hanaasagi/rikka
Author: Hanaasagi
Author-email: ambiguous404@gmail.com
License: MIT
Platform: UNKNOWN
Classifier: License :: OSI Approved :: MIT License
Classifier: Programming Language :: Python :: 3 :: Only
Classifier: Programming Language :: Python :: 3.6
Classifier: Programming Language :: Python :: 3.7
Classifier: Topic :: Internet
Classifier: Topic :: Internet :: Proxy Servers
Requires-Python: >=3.6
Requires-Dist: bidict (>=0.16.0)
